randompackage17/__init__.py
randompackage17/main.py
randompackage17-0.1.1.dist-info/METADATA
randompackage17-0.1.1.dist-info/WHEEL
randompackage17-0.1.1.dist-info/licenses/LICENSE
randompackage17-0.1.1.dist-info/RECORD
