Metadata-Version: 2.4
Name: randompackage17
Version: 0.1.1
Summary: A mastermind package
Project-URL: Homepage, https://github.com/avelusamy/randompackage
Project-URL: Issues, https://github.com/avelusamy/randompackage/issues
Author-email: Aditya Velusamy <avelusamy@pm.me>
License-Expression: Unlicense
License-File: LICENSE
Classifier: Operating System :: OS Independent
Classifier: Programming Language :: Python :: 3
Requires-Python: >=3.9
